effmass/__init__.py
effmass/_version.py
effmass/analysis.py
effmass/cli.py
effmass/dos.py
effmass/extrema.py
effmass/inputs.py
effmass/outputs.py
effmass-2.3.1.dist-info/LICENSE
effmass-2.3.1.dist-info/METADATA
effmass-2.3.1.dist-info/WHEEL
effmass-2.3.1.dist-info/entry_points.txt
effmass-2.3.1.dist-info/top_level.txt
effmass-2.3.1.dist-info/RECORD
