Metadata-Version: 2.1
Name: effmass
Version: 2.3.1
Summary: An effective mass package
Home-page: https://github.com/lucydot/effmass
Author: Lucy Whalley
Author-email: l.whalley@northumbria.ac.uk
Project-URL: Bug Tracker, https://github.com/lucydot/effmass/issues
Classifier: Programming Language :: Python :: 3
Classifier: License :: OSI Approved :: MIT License
Classifier: Operating System :: OS Independent
Requires-Python: >=3.6
License-File: LICENSE
Requires-Dist: vasppy (>=0.5.0.0)
Requires-Dist: scipy
Requires-Dist: numpy
Requires-Dist: matplotlib
Requires-Dist: adjustText
Requires-Dist: ase (>=3.21.1)
Requires-Dist: octopuspy (>=1.0.2)
Requires-Dist: questionary (>=1.9.0)
Requires-Dist: prettytable (>=2.1.0)
Requires-Dist: importlib-metadata (>=0.12) ; python_version < "3.8"
Provides-Extra: dev
Requires-Dist: black ; extra == 'dev'
Requires-Dist: build ; extra == 'dev'
Provides-Extra: docs
Requires-Dist: sphinx (>=3.2.1) ; extra == 'docs'
Requires-Dist: sphinx-rtd-theme (>=0.5.0) ; extra == 'docs'
Provides-Extra: tests
Requires-Dist: pytest ; extra == 'tests'
Requires-Dist: pytest-lazy-fixture ; extra == 'tests'
Requires-Dist: codeclimate-test-reporter ; extra == 'tests'
Requires-Dist: coverage (==4.3.4) ; extra == 'tests'
